LICENSE
README.md
setup.py
SungrowModbusWebClient/SungrowModbusWebClient.py
SungrowModbusWebClient/__init__.py
SungrowModbusWebClient/version.py
SungrowModbusWebClient.egg-info/PKG-INFO
SungrowModbusWebClient.egg-info/SOURCES.txt
SungrowModbusWebClient.egg-info/dependency_links.txt
SungrowModbusWebClient.egg-info/requires.txt
SungrowModbusWebClient.egg-info/top_level.txt