Metadata-Version: 2.1
Name: SungrowModbusWebClient
Version: 0.3.0
Summary: A ModbusWebClient wrapper for talking to Sungrow WiNet-S Dongle via HTTP API
Home-page: https://github.com/bohdan-s/SungrowModbusWebClient
Author: Bohdan Flower
Author-email: github@bohdan.net
License: UNKNOWN
Platform: UNKNOWN
Classifier: Programming Language :: Python :: 3
Classifier: License :: OSI Approved :: GNU General Public License v3 (GPLv3)
Classifier: Operating System :: OS Independent
Requires-Python: >=3.5.0
